README.txt
setup.py
src/django_templatequery/__init__.py
src/django_templatequery/models.py
src/django_templatequery/parser.py
src/django_templatequery/template.py
src/django_templatequery.egg-info/PKG-INFO
src/django_templatequery.egg-info/SOURCES.txt
src/django_templatequery.egg-info/dependency_links.txt
src/django_templatequery.egg-info/requires.txt
src/django_templatequery.egg-info/top_level.txt
src/django_templatequery/templatetags/__init__.py
src/django_templatequery/templatetags/query_tags.py
src/django_templatequery/tests/__init__.py
src/django_templatequery/tests/test_query_tags.py